tests/__init__.py
tests/conftest.py
tests/test_examples.py
tests/test_fake.py
tests/test_files.py
tests/test_imports.py
tests/test_list_shortcut.py
tests/test_mapped_signature.py
tests/test_nested_attributes.py
tests/test_ordering.py
tests/test_persistence_models.py
yorm/__init__.py
yorm/common.py
yorm/decorators.py
yorm/diskutils.py
yorm/exceptions.py
yorm/mapper.py
yorm/mixins.py
yorm/settings.py
yorm/utilities.py
yorm/bases/__init__.py
yorm/bases/converter.py
yorm/bases/mappable.py
yorm/tests/__init__.py
yorm/tests/conftest.py
yorm/tests/test_bases_container.py
yorm/tests/test_bases_converter.py
yorm/tests/test_bases_mappable.py
yorm/tests/test_decorators.py
yorm/tests/test_diskutils.py
yorm/tests/test_mapper.py
yorm/tests/test_mixins.py
yorm/tests/test_types_containers.py
yorm/tests/test_types_extended.py
yorm/tests/test_types_standard.py
yorm/tests/test_utilities.py
yorm/types/__init__.py
yorm/types/_representers.py
yorm/types/containers.py
yorm/types/extended.py
yorm/types/standard.py
YORM-1.6.2.dist-info/LICENSE.md
YORM-1.6.2.dist-info/METADATA
YORM-1.6.2.dist-info/WHEEL
YORM-1.6.2.dist-info/entry_points.txt
YORM-1.6.2.dist-info/top_level.txt
YORM-1.6.2.dist-info/RECORD
