Metadata-Version: 1.1
Name: YORM
Version: 1.6.2
Summary: Automatic object-YAML mapping for Python.
Home-page: https://github.com/jacebrowning/yorm
Author: Jace Browning
Author-email: jacebrowning@gmail.com
License: MIT
Platform: UNKNOWN
Classifier: Development Status :: 5 - Production/Stable
Classifier: Intended Audience :: Developers
Classifier: License :: OSI Approved :: MIT License
Classifier: Natural Language :: English
Classifier: Operating System :: OS Independent
Classifier: Programming Language :: Python
Classifier: Programming Language :: Python :: 3
Classifier: Programming Language :: Python :: 3.5
Classifier: Programming Language :: Python :: 3.6
Classifier: Programming Language :: Python :: 3.7
Classifier: Topic :: Database
Classifier: Topic :: Software Development :: Libraries
Classifier: Topic :: Software Development :: Version Control
Classifier: Topic :: System :: Filesystems
Classifier: Topic :: Text Editors :: Text Processing
